jupyterlab_git/__init__.py
jupyterlab_git/_version.py
jupyterlab_git/git.py
jupyterlab_git/handlers.py
jupyterlab_git/log.py
jupyterlab_git/ssh.py
jupyterlab_git/tests/__init__.py
jupyterlab_git/tests/conftest.py
jupyterlab_git/tests/test_branch.py
jupyterlab_git/tests/test_clone.py
jupyterlab_git/tests/test_config.py
jupyterlab_git/tests/test_detailed_log.py
jupyterlab_git/tests/test_diff.py
jupyterlab_git/tests/test_execute.py
jupyterlab_git/tests/test_fetch.py
jupyterlab_git/tests/test_handlers.py
jupyterlab_git/tests/test_ignore.py
jupyterlab_git/tests/test_init.py
jupyterlab_git/tests/test_integrations.py
jupyterlab_git/tests/test_jupytext.py
jupyterlab_git/tests/test_pushpull.py
jupyterlab_git/tests/test_remote.py
jupyterlab_git/tests/test_settings.py
jupyterlab_git/tests/test_single_file_log.py
jupyterlab_git/tests/test_stash.py
jupyterlab_git/tests/test_status.py
jupyterlab_git/tests/test_tag.py
jupyterlab_git/tests/testutils.py
jupyterlab_git/tests/files/inline-conflict--1.ipynb
jupyterlab_git/tests/files/inline-conflict--2.ipynb
jupyterlab_git/tests/files/inline-conflict--3.ipynb
jupyterlab_git/tests/files/multilevel-test-base.ipynb
jupyterlab_git/tests/files/multilevel-test-local.ipynb
jupyterlab_git/tests/files/multilevel-test-remote.ipynb
jupyterlab_git/tests/files/src-and-output--1.ipynb
jupyterlab_git/tests/files/src-and-output--2.ipynb
jupyterlab_git/tests/samples/ipynb_base.json
jupyterlab_git/tests/samples/ipynb_nbdiff.json
jupyterlab_git/tests/samples/ipynb_remote.json
jupyterlab_git-0.51.4.data/data/etc/jupyter/jupyter_server_config.d/jupyterlab_git.json
jupyterlab_git-0.51.4.data/data/share/jupyter/labextensions/@jupyterlab/git/package.json
jupyterlab_git-0.51.4.data/data/share/jupyter/labextensions/@jupyterlab/git/schemas/@jupyterlab/git/package.json.orig
jupyterlab_git-0.51.4.data/data/share/jupyter/labextensions/@jupyterlab/git/schemas/@jupyterlab/git/plugin.json
jupyterlab_git-0.51.4.dist-info/METADATA
jupyterlab_git-0.51.4.dist-info/WHEEL
jupyterlab_git-0.51.4.dist-info/licenses/LICENSE
jupyterlab_git-0.51.4.dist-info/RECORD
